sysq/__init__.py
sysq/__main__.py
sysq/core.py
sysq/data/file.txt
sysq-1.7.0.dist-info/entry_points.txt
sysq-1.7.0.dist-info/WHEEL
sysq-1.7.0.dist-info/METADATA
sysq-1.7.0.dist-info/RECORD
