Metadata-Version: 2.1
Name: sysq
Version: 1.7.0
Summary: demo query sys functions
Author: Your Name
Author-email: you@example.com
Requires-Python: >=3.7,<4.0
Classifier: Programming Language :: Python :: 3
Classifier: Programming Language :: Python :: 3.7
Classifier: Programming Language :: Python :: 3.8
Classifier: Programming Language :: Python :: 3.9
